Workbook

Sheet 填写说明
A1: WEBUY TRAVEL · 韩国地接资料与报价模板（v1.0 · 2026-10-08）
A3: 用途 | B3: 统一韩国地接社的资源与报价格式，填回后由 WEBUY 自动转入产品库（Lark Product Base：Suppliers / Quotes / Quote_Lines），用于比价、成本核算与行程生成。
A4: Purpose | B4: One standard format for Korea ground handlers. Returned files are imported automatically into WEBUY's product base for costing and itinerary building.
A5: 안내 | B5: WEBUY TRAVEL(싱가포르) 표준 견적 양식입니다. 노란색 셀에 입력해 주시고, 회색 셀은 WEBUY가 미리 입력한 항목입니다(수정 금지). 금액은 KRW 넷 요금(세금 포함) 기준입니다.
A6: 颜色 | B6: 黄色 = 请填写 · 灰色 = WEBUY 预填（请勿修改，可在备注补充）· 绿色 = 公式自动计算 · 浅灰斜体第 5 行 = 示例，不会读入
A7: 表头 | B7: 第 3 行为字段名（中文 / English / 한국어），第 4 行灰色小字为系统字段 key，请勿删除或改动。
A8: 币种 | B8: 默认 KRW；如用 USD / SGD 报价请在每行「币种」列注明。所有价格为净价（net），含当地税。
A9: 日期 | B9: 日期格式 YYYY-MM-DD；季节档：淡季 / 平季 / 旺季 / 节假，与 WEBUY 出发日期表一致。
A10: 新增行 | B10: 预填清单不够时直接在下方黄色空行继续填写；不够可插入行（保持列顺序）。
A11: 不能操作 | B11: 预填的酒店 / 景点如不能操作或不建议，价格留空并在「备注」写原因或替代建议。
A12: 交回 | B12: 填好后整份 Excel 交回 WEBUY Planner（请勿转成 PDF / 图片）。原始报价单可另附，但以本模板为准。
A13: 表单 | B13: 1 供应商信息 · 2 酒店 · 3 景点门票 · 4 餐食 · 5 用车交通 · 6 导游领队 · 7 购物与自费 · 8 季节节庆 · 9 行程报价 · 10 逐日行程 · Lists（下拉选项与参考汇率）
A14: 数据来源 | B14: 灰色预填来自 WEBUY 韩国线知识库（korea/kb，2026-10-08 抓取新加坡 3 家旅行社 + 首尔地接在售线路 53 条），代表市场上实际在卖的酒店、景点与路段。
A16: 请填写 Fill in
A17: WEBUY 预填 Pre-filled
A18: 自动计算 Formula
A19: 示例 Example

Sheet 1 供应商信息
A1: 1 供应商信息 Supplier Profile（韩国地接）
A2: 对应 Lark Suppliers 表 + Quotes 报价单表头。黄色格子请填写；一家地接填一份。
A3: 字段 Field | B3: 填写 Value | C3: 示例 Example | D3: key
A4: 公司名称 / Company name / 회사명 | C4: ABC Travel Co., Ltd. | D4: supplier_name
A5: 旅行社执照号 / Travel agency license no. / 여행업 등록번호 | C5: 제2026-000001호 | D5: license_no
A6: 公司地址 / Address / 주소 | D6: address
A7: 业务联系人 / 职位 / Sales contact / title / 담당자 / 직책 | C7: Kim Min-ji / Sales Manager | D7: contact_person
A8: WhatsApp / 微信 / KakaoTalk / Email / WhatsApp / WeChat / KakaoTalk / Email / 연락처 | D8: contact_channels
A9: 24 小时紧急联系电话 / 24h emergency number / 24시간 비상연락처 | D9: emergency_24h
A10: 可操作区域 / Regions covered / 운영 가능 지역 | C10: 全韩国 + 济州 | D10: regions_covered
A11: 导游语种与人数 / Guide languages & headcount / 가이드 언어 / 인원 | C11: 中文 20 / 英文 8 / 马来 2 | D11: guide_languages
A12: 自有车队（车型 × 数量） / Own fleet (type × qty) / 보유 차량 | C12: 45 座 × 10；25 座 × 4 | D12: own_coaches
A13: 接待新加坡/马来西亚团经验（年 / 年团量） / SG/MY market experience / 싱가포르·말레이시아 단체 경험 | C13: 8 年 / 约 300 团 | D13: sg_my_experience
A14: 可否操作清真 / 素食团 / Halal / vegetarian capability / 할랄 / 채식 가능 여부 | C14: 清真餐厅 6 家可用；素食可安排 | D14: halal_capable
A15: 报价币种 / Quote currency / 견적 통화 | C15: KRW | D15: quote_currency
A16: 报价有效期 起 / Valid from / 유효기간 시작 | C16: 2027-01-01 | D16: quote_valid_from
A17: 报价有效期 止 / Valid until / 유효기간 종료 | C17: 2027-12-31 | D17: quote_valid_until
A18: 付款条件（订金 / 尾款期限） / Payment terms / 결제 조건 | C18: 出发前 30 天付 30% 订金，出发前 7 天付清 | D18: payment_terms
A19: 取消政策 / Cancellation policy / 취소 규정 | C19: 出发前 14 天取消收 30%…… | D19: cancellation_policy
A20: 旅行社责任险（保额） / Liability insurance (coverage) / 여행자 배상책임보험 | D20: liability_insurance
A21: 报价是否含税（VAT） / Price incl. VAT? / 부가세 포함 여부 | C21: Y | D21: price_includes_tax
A22: 其他说明 / Other notes / 기타 | D22: notes

Sheet 2 酒店
A1: 2 酒店 Hotels
A2: 已预填竞品在售线路出现过的 88 家酒店（灰色）。请对能操作的酒店填价，不能操作的留空；可在下方黄色空行补充推荐酒店。价格为每间每晚净价。
A3: 城市 City 도시 | B3: 酒店名称（英文） Hotel name (EN) 호텔명 (영문) | C3: WEBUY 档次参考 Tier seen in market 시장 등급 | D3: 当地名称 Local name 현지명 | E3: 星级 Star 등급 | F3: 区域 / 商圈 Area 지역 | G3: 房型 Room type 객실 타입 | H3: 季节档 Season 시즌 | I3: 适用日期 起 From 적용 시작 | J3: 适用日期 止 To 적용 종료 | K3: 双人房 / 间 / 晚（KRW） Twin per room/night (KRW) 트윈 1실 1박 | L3: 单人房 / 间 / 晚（KRW） Single per room/night (KRW) 싱글 1실 1박 | M3: 三人房 / 间 / 晚（KRW） Triple per room/night (KRW) 트리플 1실 1박 | N3: 加床（KRW） Extra bed (KRW) 엑스트라 베드 | O3: 含早餐 Breakfast incl. 조식 포함 | P3: 早餐单价（KRW） Breakfast / pax (KRW) 조식 단가 | Q3: 儿童政策（年龄 / 不占床） Child policy 아동 규정 | R3: 团体价最少间数 Min rooms for group rate 단체 최소 객실 | S3: 大巴可停 Coach parking 버스 주차 | T3: 可保留房量（间 / 晚） Allotment (rooms/night) 블록 객실 수 | U3: 释放期（出发前天数） Release (days before) 릴리즈 기한 | V3: 备注（加价日 / 施工 / 新开） Notes 비고
A4: city | B4: hotel_name_en | C4: webuy_tier | D4: hotel_name_local | E4: star | F4: area | G4: room_type | H4: season | I4: date_from | J4: date_to | K4: twin_per_room | L4: single_per_room | M4: triple_per_room | N4: extra_bed | O4: breakfast_incl | P4: breakfast_price | Q4: child_policy | R4: group_min_rooms | S4: coach_parking | T4: allotment | U4: release_days | V4: notes
A5: 首尔 Seoul | B5: Novotel Ambassador Seoul Yongsan | C5: group_standard | D5: 노보텔 앰배서더 서울 용산 | E5: 4★ | F5: 龙山 Yongsan | G5: Superior Twin | H5: 平季 Shoulder | I5: 46447 | J5: 46568 | K5: 180000 | L5: 170000 | M5: 240000 | N5: 50000 | O5: Y | P5: 35000 | Q5: 12 岁以下不占床免费（不含早） | R5: 8 | S5: Y | T5: 20 | U5: 21 | V5: 4/1–4/10 樱花期加价 20%
A6: 首尔 Seoul | B6: Golden Seoul Hotel/ Ibis Ambassador Yongsan Hotel | C6: fit
A7: 首尔 Seoul | B7: Ibis Ambassador Yongsan Seoul | C7: group_standard
A8: 首尔 Seoul | B8: Novotel Ambassador Seoul Yongsan | C8: group_standard
A9: 首尔 Seoul | B9: Novotel Ambassador Yongsan | C9: group_standard
A10: 首尔 Seoul | B10: Seoul Bernoui Hote | C10: group_standard
A11: 首尔 Seoul | B11: Seoul Garden hotel | C11: group_standard
A12: 首尔 Seoul | B12: Seoul Novotel Ambassador | C12: group_standard
A13: 首尔 Seoul | B13: Seoul Novotel Hotel | C13: group_standard
A14: 首尔 Seoul | B14: Sollago Myeongdong Hotel | C14: group_standard
A15: 首尔 Seoul | B15: Amanti Seoul | C15: premium
A16: 首尔 Seoul | B16: Amanty Hotel | C16: premium
A17: 首尔 Seoul | B17: Amid Hotel Seoul | C17: premium
... A93: 光州 Gwangju | B93: Holiday Inn Gwangju | C93: join_in

Sheet 3 景点门票
A1: 3 景点门票 Attractions & Tickets
A2: 已预填竞品线路出现过的 245 个景点（按 核心 → 常见 → 可选 排序）。请填写门票与团体价、开放与预约要求；不再营业或不建议的请在备注写替代景点；可在下方空行补充地接推荐景点。
A3: 城市 City 도시 | B3: 景点（英文） Attraction (EN) 관광지 (영문) | C3: 景点（中文） Attraction (CN) 관광지 (중문) | D3: 类别 Category 분류 | E3: 市场热度 Market level 시장 인기도 | F3: 当地名称 Local name 현지명 | G3: 建议停留（小时） Suggested stay (h) 권장 체류 | H3: 开放时间 Opening hours 운영 시간 | I3: 休息日 Closed days 휴무일 | J3: 成人门票（KRW） Adult ticket (KRW) 성인 입장료 | K3: 儿童门票（KRW） Child ticket (KRW) 아동 입장료 | L3: 团体价 / 人（KRW） Group rate/pax (KRW) 단체 요금 | M3: 团体价最少人数 Group min pax 단체 최소 인원 | N3: 免费政策（导游 / 司机 / FOC） Free policy 무료 규정 | O3: 需预约（提前天数，0=不需） Booking lead days 예약 필요 일수 | P3: 大巴可停 Coach parking 버스 주차 | Q3: 最佳月份 / 季节限制 Best months / seasonal limits 추천 시기 | R3: 适合 Suitable for 적합 유형 | S3: 清真友好（祈祷室 / 餐） Muslim-friendly 무슬림 친화 | T3: 备注（施工 / 关闭 / 替代景点） Notes 비고
A4: city | B4: name_en | C4: name_cn | D4: category | E4: webuy_level | F4: name_local | G4: duration_h | H4: opening_hours | I4: closed_days | J4: adult_ticket | K4: child_ticket | L4: group_rate | M4: group_min_pax | N4: free_policy | O4: reservation_days | P4: coach_parking | Q4: best_months | R4: suitable | S4: halal_friendly | T4: notes
A5: 首尔 Seoul | B5: Gyeongbokgung Palace | C5: 景福宫 | D5: 宫殿 | E5: 核心 Core | F5: 경복궁 | G5: 1.5 | H5: 09:00–18:00 | I5: 周二 | J5: 3000 | K5: 0 | L5: 2400 | M5: 10 | N5: 穿韩服免费入场 | O5: 0 | P5: Y | Q5: 全年 | R5: Both 均可 | S5: N | T5: 周二休馆时改德寿宫
A6: 江华岛 Ganghwa | B6: Ganghwa Peace Observatory | C6: 江华和平展望台 | D6: 安保观光（DMZ） | E6: 核心 Core
A7: 江华岛 Ganghwa | B7: Joyang Bangjik Café (Ganghwa) | C7: 江华朝阳纺织咖啡 | D7: 网红咖啡/拍照点 | E7: 核心 Core
A8: 加平 Gapyeong | B8: The Garden of Morning Calm | C8: 晨静树木园 | D8: 公园/花园/树木园 | E8: 核心 Core
A9: 金浦 Gimpo | B9: Aegibong Peace Ecopark | C9: 爱妓峰和平生态公园 | D9: 安保观光（DMZ） | E9: 核心 Core
A10: 金浦 Gimpo | B10: Rice Flower's Farmer (Gimpo) | C10: 金浦米花农场 | D10: 农场/采摘 | E10: 核心 Core
A11: 金浦 Gimpo | B11: Hyundai Premium Outlet Gimpo | C11: 金浦现代名品奥特莱斯 | D11: 奥特莱斯/商场 | E11: 核心 Core
A12: 仁川 Incheon | B12: Songwol-dong Fairy Tale Village | C12: 松月洞童话村 | D12: 传统村落/韩屋村 | E12: 核心 Core
A13: 仁川 Incheon | B13: Incheon Chinatown & Jjajangmyeon Museum | C13: 仁川中华街·炸酱面博物馆 | D13: 街区/商圈 | E13: 核心 Core
A14: 仁川 Incheon | B14: Incheon Open Port Street | C14: 仁川开港场街 | D14: 街区/商圈 | E14: 核心 Core
A15: 抱川 Pocheon | B15: Pocheon Art Valley | C15: 抱川艺谷 | D15: 公园/花园/树木园 | E15: 核心 Core
A16: 首尔 Seoul | B16: Myeongdong Shopping Street | C16: 明洞购物街 | D16: 街区/商圈 | E16: 核心 Core
A17: 首尔 Seoul | B17: Gyeongbokgung Palace | C17: 景福宫 | D17: 宫殿 | E17: 核心 Core
... A250: 泰安 Taean | B250: Taean Thalassotherapy & Tulip Festival | C250: 泰安海洋疗养·郁金香节 | D250: 体验 | E250: 可选 Optional

Sheet 4 餐食
A1: 4 餐食 Meals
A2: 灰色为竞品团常见团餐（请对应报价、推荐餐厅）；黄色空行补充其他团餐与特色餐。价格为每人净价，含税。
A3: 城市 City 도시 | B3: 餐名 / 菜单 Meal / menu 메뉴 | C3: 餐厅名称 Restaurant 식당명 | D3: 餐别 Meal 식사 구분 | E3: 菜系 / 特色 Cuisine / highlight 음식 종류 | F3: 成人 / 人（KRW） Adult/pax (KRW) 성인 1인 | G3: 儿童 / 人（KRW） Child/pax (KRW) 아동 1인 | H3: 最少人数 Min pax 최소 인원 | I3: 可容纳人数 Seating capacity 수용 인원 | J3: 清真 Halal 할랄 | K3: 素食可替换 Vegetarian option 채식 대체 | L3: 可不含牛肉 No-beef option 소고기 제외 | M3: 大巴可停 Coach parking 버스 주차 | N3: 备注 Notes 비고
A4: city | B4: meal_name | C4: restaurant | D4: meal_type | E4: cuisine | F4: price_adult | G4: price_child | H4: min_pax | I4: capacity | J4: halal | K4: vegetarian | L4: no_beef | M4: coach_parking | N4: notes
A5: 首尔 Seoul | B5: 参鸡汤 + 海鲜煎饼 | C5: 土俗村参鸡汤 | D5: L | E5: 韩式 / 米其林指南推荐 | F5: 22000 | G5: 15000 | H5: 10 | I5: 120 | J5: N | K5: Y | L5: Y | M5: N | N5: 大巴需停景福宫停车场，步行 5 分钟
A6: 首尔 Seoul | B6: 参鸡汤 Ginseng chicken soup
A7: 首尔 Seoul | B7: 韩式烤肉（猪/牛）Korean BBQ
A8: 首尔 Seoul | B8: 部队锅 Army stew
A9: 首尔 Seoul | B9: 韩定食 Hanjeongsik
A10: 济州 Jeju | B10: 济州黑猪烤肉 Jeju black pork
A11: 济州 Jeju | B11: 带鱼 / 青花鱼套餐 Hairtail & mackerel set
A12: 济州 Jeju | B12: 海鲜锅 Seafood hotpot
A13: 釜山 Busan | B13: 猪肉汤饭 Dwaeji-gukbap
A14: 釜山 Busan | B14: 海鲜 / 生鱼片套餐 Sashimi set
A15: 全州 Jeonju | B15: 全州石锅拌饭 Jeonju bibimbap
A16: 春川 Chuncheon | B16: 春川辣炒鸡排 Dakgalbi
A17: 安东 Andong | B17: 安东炖鸡 Andong jjimdak
... A19: 首尔 Seoul | B19: 清真韩餐 Halal Korean set

Sheet 5 用车交通
A1: 5 用车与交通 Transport
A2: 灰色为常用用车项目与竞品线路实际出现过的城市路段（次数=出现的线路数）。请按车型填价；国内段机票/KTX 请填团体票价与出票条件。
A3: 项目 / 路段 Item / segment 항목 / 구간 | B3: 方式 Mode 교통수단 | C3: 竞品线路出现次数 Seen in market tours 시장 노출 | D3: 车型 Vehicle 차종 | E3: 车程 / 航程 Duration 소요 시간 | F3: 价格（KRW） Price (KRW) 요금 | G3: 计价单位 Price unit 단위 | H3: 已含（油/路桥/停车/司机食宿） Included 포함 사항 | I3: 超时 / 小时（KRW） Overtime/h (KRW) 초과 시간당 | J3: 备注 Notes 비고
A4: item | B4: mode | C4: market_seen | D4: vehicle | E4: duration | F4: price | G4: price_unit | H4: included | I4: ot_per_hour | J4: notes
A5: 大巴日租（10 小时，市内） | B5: Coach | D5: 45 seats | E5: 10h | F5: 900000 | G5: 每车每天 | H5: 油、路桥、停车；不含司机住宿 | I5: 60000 | J5: 跨道过夜另加司机房 1 间
A6: 大巴日租（10 小时，市内） | B6: Coach
A7: 大巴超长日（跨道 ≥ 300 km） | B7: Coach
A8: 仁川机场 ICN 接 / 送 | B8: Coach
A9: 金浦机场 GMP 接 / 送 | B9: Coach
A10: 金海机场 PUS 接 / 送 | B10: Coach
A11: 济州机场 CJU 接 / 送 | B11: Coach
A12: 济州环岛大巴日租 | B12: Coach
A13: 国内段 GMP–CJU（团体票） | B13: Flight
A14: 国内段 CJU–PUS（团体票） | B14: Flight
A15: 国内段 GMP–PUS（团体票） | B15: Flight
A16: KTX 首尔–釜山 | B16: KTX
A17: KTX 首尔–江陵 | B17: KTX
... A20: 浦项–郁陵岛高速船 | B20: Ferry
A21: 平昌 → 首尔 | B21: Coach / Bus / Flight (CJU-GMP) | C21: 8
A22: 全州 → 首尔 | B22: Bus / Coach | C22: 6
A23: 釜山 → 庆州 | B23: Bus / Coach | C23: 6
A24: 济州 → 釜山 | B24: Flight | C24: 5
A25: 济州 → 大邱 | B25: Flight / Bus / Bus / Flight | C25: 4
A26: 庆州 → 平昌 | B26: Bus / Coach | C26: 4
A27: 釜山 → 首尔 | B27: Coach / Flight | C27: 4
A28: 大邱 → 全州 | B28: Bus | C28: 3
A29: 全州 → 光州 | B29: Coach | C29: 3
A30: 光州 → 釜山 | B30: Coach | C30: 3
A31: 横城 → 首尔 | B31: Car / Bus | C31: 2
A32: 釜山 → 大邱 | B32: Bus | C32: 2
... A40: 首尔 → 济州 | B40: Flight / Flight (GMP-CJU) | C40: 2

Sheet 6 导游领队
A1: 6 导游 / 领队 / 小费 Guides & Tips
A2: 填写导游费用与建议小费（WEBUY 会写进行程「不含」与「服务费」）。
A3: 角色 Role 역할 | B3: 语种 Language 언어 | C3: 日薪（KRW） Fee/day (KRW) 일당 | D3: 餐补 / 天（KRW） Meal allowance/day (KRW) 식대 | E3: 需另付住宿 Room needed 숙박 필요 | F3: 建议小费 / 人 / 天（KRW） Tips/pax/day (KRW) 팁 가이드 | G3: FOC 政策（如 15+1） FOC policy FOC 규정 | H3: 备注 Notes 비고
A4: role | B4: language | C4: fee_per_day | D4: meal_allowance | E4: room_needed | F4: tips_guideline | G4: foc_policy | H4: notes
A5: 中文导游 Mandarin guide | B5: 中文 Mandarin | C5: 200000 | D5: 30000 | E5: Y | F5: 10000 | G5: 15+1（第 16 位免费） | H5: EU Holidays 韩国线向客人收服务费 KRW 90,000 / 人（8D6N）
A6: 中文导游 Mandarin guide
A7: 英文导游 English guide
A8: 司机兼导游 Driver-guide
A9: 送机 / 接机助理 Airport assistant

Sheet 7 购物与自费
A1: 7 购物站与自费 Shopping stops & Optional tours
A2: 竞品跟团 91% 含购物站（人参 / 护肝宝 / 化妆品最常见）。请列出你们的标准购物站、人头费与「免购物」加价，以便 WEBUY 做纯玩与常规两个版本。
A3: 名称 Name 명칭 | B3: 类型 Type 유형 | C3: 城市 City 도시 | D3: 停留（分钟） Stay (min) 체류 (분) | E3: 自费价格 / 人（KRW） Optional price/pax (KRW) 선택관광 요금 | F3: 人头费 / 人（KRW） Rebate per head (KRW) 인두비 | G3: 佣金比例 Commission % 커미션 | H3: 是否必进 Mandatory 필수 여부 | I3: 备注（可否免购物 / 免购物加价） Notes (no-shopping surcharge) 비고
A4: name | B4: type | C4: city | D4: stay_minutes | E4: price | F4: rebate_per_head | G4: commission_pct | H4: mandatory | I4: notes
A5: 高丽人参店 Ginseng | B5: 购物站 Shopping stop | C5: 首尔 Seoul | D5: 60 | F5: 20000 | G5: 0.1 | H5: Y | I5: 全程不进购物站每人加 KRW 60,000
A6: 高丽人参店 Ginseng | B6: 购物站 Shopping stop
A7: 护肝宝店 Healthy liver (Hovenia) | B7: 购物站 Shopping stop
A8: 化妆品店 Cosmetics | B8: 购物站 Shopping stop
A9: 紫水晶店 Amethyst | B9: 购物站 Shopping stop
A10: 免税店 Duty-free | B10: 购物站 Shopping stop
A11: 头皮护理 Scalp care | B11: 购物站 Shopping stop
A12: 乐天超市 Lotte Mart | B12: 购物站 Shopping stop
A13: 乱打秀 NANTA show | B13: 自费 Optional tour
A14: 汉江游船 Han River cruise | B14: 自费 Optional tour
A15: 乐天世界塔 Seoul Sky | B15: 自费 Optional tour
A16: 釜山游艇 Busan yacht | B16: 自费 Optional tour
A17: 滑雪装备 + 教练 Ski package | B17: 自费 Optional tour

Sheet 8 季节节庆
A1: 8 季节与节庆 Seasons & Events
A2: 灰色为 WEBUY 掌握的季节窗口；请填 2027 确切日期、酒店加价与操作建议，可补充其他节庆。
A3: 季节 / 节庆 Season / event 시즌 / 축제 | B3: WEBUY 参考时间 Reference window 참고 시기 | C3: 2027 确切日期 2027 exact dates 2027 일정 | D3: 影响城市 Cities affected 영향 도시 | E3: 酒店加价 % Hotel surcharge % 호텔 할증 | F3: 是否不能接团 Blackout 접수 불가 | G3: 地接建议（必去 / 回避 / 替代） DMC advice 추천 / 대체 | H3: 备注 Notes 비고
A4: event | B4: webuy_window | C4: dates_2027 | D4: city | E4: hotel_surcharge_pct | F4: blackout | G4: recommend | H4: notes
A5: 镇海军港节樱花 | B5: 3 月下旬–4 月上旬 | C5: 2027-03-27 ~ 04-05 | D5: 昌原（镇海）/ 釜山 | E5: 0.3 | F5: N | G5: 大巴只能停外围，需改坐接驳车
A6: 樱花（首尔/京畿） | B6: 3 月底–4 月上旬
A7: 镇海军港节樱花 | B7: 3 月下旬–4 月上旬（约 10 天）
A8: 济州樱花 / 油菜花 | B8: 3 月中–4 月上旬
A9: 光阳梅花 / 求礼山茱萸 | B9: 3 月上中旬
A10: 泰安郁金香节 | B10: 4 月中–5 月上旬
A11: 济州绣球花 | B11: 6 月中–7 月中
A12: 保宁泥浆节 | B12: 7 月中下旬（约 10 天）
A13: 粉黛乱子草 | B13: 9 月下旬–10 月
A14: 赏枫 / 银杏 | B14: 10 月中–11 月中（雪岳山最早、内藏山最晚）
A15: 釜山烟花节 | B15: 11 月初（单日）
A16: 滑雪 | B16: 12 月中–2 月底
A17: 华川山鳟鱼冰钓节 | B17: 1 月（约 3 周）
... A29: 新加坡学校假期 | B29: 6 月、11 月中 ~ 12 月

Sheet 9 行程报价
A1: 9 行程报价 Package Quote（按 出发期 × 人数档 一行）
A2: 对应 Lark Quotes / Quote_Lines。灰色为 WEBUY 询价线路与人数档；请按出发期段填写每人净价（同一线路不同季节可复制行）。行程细节请填「10 逐日行程」。绿色列自动计算。
A3: 询价编号 RFQ code 견적 요청 번호 | B3: 线路骨架 Itinerary skeleton 일정 개요 | C3: 天数 Days 일수 | D3: 酒店档次 Hotel level 호텔 등급 | E3: 出发期 起 Departure from 출발 시작 | F3: 出发期 止 Departure to 출발 종료 | G3: 季节档 Season 시즌 | H3: 人数档 Pax tier 인원 구간 | I3: 币种 Currency 통화 | J3: 成人 / 人（两人一房） Adult/pax twin 성인 1인 (2인 1실) | K3: 单房差 Single supplement 싱글 차액 | L3: 儿童占床 Child w/ bed 아동 베드 포함 | M3: 儿童不占床 Child no bed 아동 베드 미포함 | N3: 三人房 / 人 Triple/pax 트리플 1인 | O3: FOC（如 15+1） FOC FOC | P3: SGD 参考价（自动） SGD ref. (auto) SGD 환산 (자동) | Q3: 含餐（B/L/D 次数） Meals incl. (B/L/D) 식사 포함 | R3: 含门票 Tickets incl. 입장료 포함 | S3: 含导游 Guide incl. 가이드 포함 | T3: 含小费 Tips incl. 팁 포함 | U3: 含国内段机票 / 高铁 Domestic flight/rail incl. 국내선/KTX 포함 | V3: 购物站数 Shopping stops 쇼핑 횟수 | W3: 备注（附加费 / 不含项） Notes 비고
A4: rfq_code | B4: itinerary | C4: days | D4: hotel_level | E4: date_from | F4: date_to | G4: season | H4: pax_tier | I4: currency | J4: price_twin | K4: single_supp | L4: child_with_bed | M4: child_no_bed | N4: triple | O4: foc | P4: price_twin_sgd | Q4: meals_count | R4: incl_tickets | S4: incl_guide | T4: incl_tips | U4: incl_domestic_transport | V4: shopping_stops | W4: notes
A5: RFQ-K04 | B5: 济州 2N > 釜山 2N > 首尔 2N | C5: 8 | D5: 4★ | E5: 46492 | F5: 46568 | G5: 平季 Shoulder | H5: 21–25 | I5: KRW | J5: 1150000 | K5: 380000 | L5: 1100000 | M5: 900000 | N5: 1120000 | O5: 15+1 | P5: =IF(OR(J5="",I5=""),"",J5*INDEX(Lists!$B$21:$B$23,MATCH(I5,Lists!$A$21:$A$23,0))) -> 1081 | Q5: 6B 6L 5D | R5: Y | S5: Y | T5: N | U5: Y | V5: 3 | W5: 4/1–4/10 樱花期每人 +KRW 50,000
A6: RFQ-K04 | B6: 济州 > 釜山 > 首尔（三城两段内陆航班）：济州 2N > 釜山 2N > 首尔 2N | C6: 8 | D6: 4★ | H6: 10–15 | P6: =IF(OR(J6="",I6=""),"",J6*INDEX(Lists!$B$21:$B$23,MATCH(I6,Lists!$A$21:$A$23,0)))
A7: RFQ-K04 | B7: 济州 > 釜山 > 首尔（三城两段内陆航班）：济州 2N > 釜山 2N > 首尔 2N | C7: 8 | D7: 4★ | H7: 16–20 | P7: =IF(OR(J7="",I7=""),"",J7*INDEX(Lists!$B$21:$B$23,MATCH(I7,Lists!$A$21:$A$23,0)))
A8: RFQ-K04 | B8: 济州 > 釜山 > 首尔（三城两段内陆航班）：济州 2N > 釜山 2N > 首尔 2N | C8: 8 | D8: 4★ | H8: 21–25 | P8: =IF(OR(J8="",I8=""),"",J8*INDEX(Lists!$B$21:$B$23,MATCH(I8,Lists!$A$21:$A$23,0)))
A9: RFQ-K04 | B9: 济州 > 釜山 > 首尔（三城两段内陆航班）：济州 2N > 釜山 2N > 首尔 2N | C9: 8 | D9: 4★ | H9: 26–30 | P9: =IF(OR(J9="",I9=""),"",J9*INDEX(Lists!$B$21:$B$23,MATCH(I9,Lists!$A$21:$A$23,0)))
A10: RFQ-K04 | B10: 济州 > 釜山 > 首尔（三城两段内陆航班）：济州 2N > 釜山 2N > 首尔 2N | C10: 8 | D10: 4★ | H10: 31–35 | P10: =IF(OR(J10="",I10=""),"",J10*INDEX(Lists!$B$21:$B$23,MATCH(I10,Lists!$A$21:$A$23,0)))
A11: RFQ-K05 | B11: 大韩全景（济州 > 庆尚 > 全州/江原 > 首尔，陆路北上）：济州 2N > 大邱 1N > 全州 1N > 首尔 2N | C11: 8 | D11: 4★ | H11: 10–15 | P11: =IF(OR(J11="",I11=""),"",J11*INDEX(Lists!$B$21:$B$23,MATCH(I11,Lists!$A$21:$A$23,0)))
A12: RFQ-K05 | B12: 大韩全景（济州 > 庆尚 > 全州/江原 > 首尔，陆路北上）：济州 2N > 大邱 1N > 全州 1N > 首尔 2N | C12: 8 | D12: 4★ | H12: 16–20 | P12: =IF(OR(J12="",I12=""),"",J12*INDEX(Lists!$B$21:$B$23,MATCH(I12,Lists!$A$21:$A$23,0)))
A13: RFQ-K05 | B13: 大韩全景（济州 > 庆尚 > 全州/江原 > 首尔，陆路北上）：济州 2N > 大邱 1N > 全州 1N > 首尔 2N | C13: 8 | D13: 4★ | H13: 21–25 | P13: =IF(OR(J13="",I13=""),"",J13*INDEX(Lists!$B$21:$B$23,MATCH(I13,Lists!$A$21:$A$23,0)))
A14: RFQ-K05 | B14: 大韩全景（济州 > 庆尚 > 全州/江原 > 首尔，陆路北上）：济州 2N > 大邱 1N > 全州 1N > 首尔 2N | C14: 8 | D14: 4★ | H14: 26–30 | P14: =IF(OR(J14="",I14=""),"",J14*INDEX(Lists!$B$21:$B$23,MATCH(I14,Lists!$A$21:$A$23,0)))
A15: RFQ-K05 | B15: 大韩全景（济州 > 庆尚 > 全州/江原 > 首尔，陆路北上）：济州 2N > 大邱 1N > 全州 1N > 首尔 2N | C15: 8 | D15: 4★ | H15: 31–35 | P15: =IF(OR(J15="",I15=""),"",J15*INDEX(Lists!$B$21:$B$23,MATCH(I15,Lists!$A$21:$A$23,0)))
A16: RFQ-K06 | B16: 釜山 + 庆州 + 首尔（南北纵贯）：釜山 2N > 庆州 1N > 首尔 3N | C16: 8 | D16: 4★ | H16: 10–15 | P16: =IF(OR(J16="",I16=""),"",J16*INDEX(Lists!$B$21:$B$23,MATCH(I16,Lists!$A$21:$A$23,0)))
A17: RFQ-K06 | B17: 釜山 + 庆州 + 首尔（南北纵贯）：釜山 2N > 庆州 1N > 首尔 3N | C17: 8 | D17: 4★ | H17: 16–20 | P17: =IF(OR(J17="",I17=""),"",J17*INDEX(Lists!$B$21:$B$23,MATCH(I17,Lists!$A$21:$A$23,0)))
... A35: RFQ-K01 | B35: 首尔 + 京畿深度：首尔 5N（每日放射） | C35: 7 | D35: 4★ | H35: 31–35 | P35: =IF(OR(J35="",I35=""),"",J35*INDEX(Lists!$B$21:$B$23,MATCH(I35,Lists!$A$21:$A$23,0)))
P36: =IF(OR(J36="",I36=""),"",J36*INDEX(Lists!$B$21:$B$23,MATCH(I36,Lists!$A$21:$A$23,0)))
P37: =IF(OR(J37="",I37=""),"",J37*INDEX(Lists!$B$21:$B$23,MATCH(I37,Lists!$A$21:$A$23,0)))
P38: =IF(OR(J38="",I38=""),"",J38*INDEX(Lists!$B$21:$B$23,MATCH(I38,Lists!$A$21:$A$23,0)))
P39: =IF(OR(J39="",I39=""),"",J39*INDEX(Lists!$B$21:$B$23,MATCH(I39,Lists!$A$21:$A$23,0)))
P40: =IF(OR(J40="",I40=""),"",J40*INDEX(Lists!$B$21:$B$23,MATCH(I40,Lists!$A$21:$A$23,0)))
P41: =IF(OR(J41="",I41=""),"",J41*INDEX(Lists!$B$21:$B$23,MATCH(I41,Lists!$A$21:$A$23,0)))
P42: =IF(OR(J42="",I42=""),"",J42*INDEX(Lists!$B$21:$B$23,MATCH(I42,Lists!$A$21:$A$23,0)))
P43: =IF(OR(J43="",I43=""),"",J43*INDEX(Lists!$B$21:$B$23,MATCH(I43,Lists!$A$21:$A$23,0)))
P44: =IF(OR(J44="",I44=""),"",J44*INDEX(Lists!$B$21:$B$23,MATCH(I44,Lists!$A$21:$A$23,0)))
P45: =IF(OR(J45="",I45=""),"",J45*INDEX(Lists!$B$21:$B$23,MATCH(I45,Lists!$A$21:$A$23,0)))
P46: =IF(OR(J46="",I46=""),"",J46*INDEX(Lists!$B$21:$B$23,MATCH(I46,Lists!$A$21:$A$23,0)))
P47: =IF(OR(J47="",I47=""),"",J47*INDEX(Lists!$B$21:$B$23,MATCH(I47,Lists!$A$21:$A$23,0)))
... P55: =IF(OR(J55="",I55=""),"",J55*INDEX(Lists!$B$21:$B$23,MATCH(I55,Lists!$A$21:$A$23,0)))

Sheet 10 逐日行程
A1: 10 逐日行程 Day-by-day Plan
A2: 每个询价编号一组逐日行程，WEBUY 会用它生成双语行程 PDF 并跑合理性校验（景点归属、车程、季节）。
A3: 询价编号 RFQ code 견적 요청 번호 | B3: 天 Day 일차 | C3: 城市路线 Route 이동 경로 | D3: 交通（车程 / 航班） Transport 교통 | E3: 景点（用「3 景点门票」里的名称，顿号分隔） Attractions 관광지 | F3: 早餐 Breakfast 조식 | G3: 午餐 Lunch 중식 | H3: 晚餐 Dinner 석식 | I3: 住宿酒店 Hotel 숙박 | J3: 当天车程（小时） Driving hours 운전 시간 | K3: 购物站 Shopping stop 쇼핑 | L3: 备注（季节替代方案） Notes 비고
A4: rfq_code | B4: day | C4: route | D4: transport | E4: attractions | F4: breakfast | G4: lunch | H4: dinner | I4: hotel | J4: driving_hours | K4: shopping | L4: notes
A5: RFQ-K04 | B5: 2 | C5: 仁川 > 金浦 ✈ 济州 | D5: 大巴 1h + GMP–CJU 1h10m | E5: 爱妓峰和平生态公园、金浦米花农场、雪绿茶博物馆 | F5: 机上 | G5: 石锅拌饭 | H5: 韩定食 | I5: Jeju Best Western 或同级 | J5: 3 | L5: 12–3 月牛岛停航改城山日出峰

Sheet Lists
A1: 下拉选项（勿改）
A3: yn | B3: season | C3: currency | D3: star | E3: meal | F3: suit | G3: tier | H3: lang | I3: vehicle | J3: shoptype | K3: level
A4: Y | B4: 淡季 Low | C4: KRW | D4: 3★ | E4: B | F4: Group 团体 | G4: 10–15 | H4: 中文 Mandarin | I4: 9 seats (van) | J4: 购物站 Shopping stop | K4: 核心 Core
A5: N | B5: 平季 Shoulder | C5: USD | D5: 4★ | E5: L | F5: FIT 散客 | G5: 16–20 | H5: English | I5: 15 seats | J5: 自费 Optional tour | K5: 常见 Common
B6: 旺季 Peak | C6: SGD | D6: 5★ | E6: D | F6: Both 均可 | G6: 21–25 | H6: 粤语 Cantonese | I6: 25 seats | K6: 可选 Optional
B7: 节假 Holiday | D7: Resort | E7: Snack | G7: 26–30 | H7: Malay | I7: 35 seats | K7: 地接推荐 DMC pick
D8: Hanok / 韩屋 | G8: 31–35 | H8: 日本語 | I8: 45 seats
D9: Glamping | G9: 36+
A20: 参考汇率（1 单位外币 = ? SGD）
A21: KRW | B21: 0.00094
A22: USD | B22: 1.29
A23: SGD | B23: 1
A24: 假设：2026-10 参考汇率，仅用于报价表「SGD 参考价」列；正式成本以 Lark FX_Rates 表为准（A4 自动重算）。
