Workbook

Sheet 填寫說明
A1: WEBUY TRAVEL · 台灣地接資料與報價模板（v1.0 · 2026-10-08）
A3: 用途 | B3: 統一台灣地接社的資源與報價格式，填回後由 WEBUY 自動轉入產品庫（Lark Product Base：Suppliers / Quotes / Quote_Lines），用於比價、成本核算與行程生成。
A4: Purpose | B4: One standard format for Taiwan ground handlers. Returned files are imported automatically into WEBUY's product base for costing and itinerary building.
A5: 顏色 | B5: 黃色 = 請填寫 · 灰色 = WEBUY 預填（請勿修改，可在備註補充）· 綠色 = 公式自動計算 · 淺灰斜體第 5 行 = 示例，不會讀入
A6: 表頭 | B6: 第 3 行為欄位名（中文 / English），第 4 行灰色小字為系統欄位 key，請勿刪除或改動。
A7: 幣種 | B7: 預設 TWD；如用 USD / SGD 報價請在每行「幣種」列註明。所有價格為淨價（net），含當地稅。
A8: 日期 | B8: 日期格式 YYYY-MM-DD；季節檔：淡季 / 平季 / 旺季 / 節假，與 WEBUY 出發日期表一致。
A9: 新增行 | B9: 預填清單不夠時直接在下方黃色空行繼續填寫；不夠可插入行（保持列順序）。
A10: 不能操作 | B10: 預填的飯店 / 景點如不能操作或不建議，價格留空並在「備註」寫原因或替代建議。
A11: 交回 | B11: 填好後整份 Excel 交回 WEBUY Planner（請勿轉成 PDF / 圖片）。原始報價單可另附，但以本模板為準。
A12: 表單 | B12: 1 供應商資訊 · 2 飯店 · 3 景點門票 · 4 餐食 · 5 用車交通 · 6 導遊領隊 · 7 購物與自費 · 8 季節節慶 · 9 行程報價 · 10 逐日行程 · Lists（下拉選項與參考匯率）
A13: 資料來源 | B13: 灰色預填為 WEBUY 整理的台灣團體常用景點 / 路段 / 節慶清單（尚無競品抓取資料），請地接按實際資源修正與補充。
A15: 請填寫 Fill in
A16: WEBUY 預填 Pre-filled
A17: 自動計算 Formula
A18: 示例 Example

Sheet 1 供應商資訊
A1: 1 供應商資訊 Supplier Profile（台灣地接）
A2: 對應 Lark Suppliers 表 + Quotes 報價單表頭。黃色格子請填寫；一家地接填一份。
A3: 欄位 Field | B3: 填寫 Value | C3: 示例 Example | D3: key
A4: 公司名稱 / Company name | C4: ABC Travel Co., Ltd. | D4: supplier_name
A5: 旅行社執照號 / Travel agency license no. | C5: 交觀甲 0000 | D5: license_no
A6: 公司地址 / Address | D6: address
A7: 業務聯絡人 / 職位 / Sales contact / title | C7: 王小明 / 業務經理 | D7: contact_person
A8: WhatsApp / 微信 / LINE / Email / WhatsApp / WeChat / LINE / Email | D8: contact_channels
A9: 24 小時緊急聯絡電話 / 24h emergency number | D9: emergency_24h
A10: 可操作區域 / Regions covered | C10: 全台灣本島 + 離島（澎湖/金門） | D10: regions_covered
A11: 導遊語種與人數 / Guide languages & headcount | C11: 中文 20 / 英文 8 / 馬來 2 | D11: guide_languages
A12: 自有車隊（車型 × 數量） / Own fleet (type × qty) | C12: 45 座 × 10；25 座 × 4 | D12: own_coaches
A13: 接待新加坡/馬來西亞團經驗（年 / 年團量） / SG/MY market experience | C13: 8 年 / 約 300 團 | D13: sg_my_experience
A14: 可否操作清真 / 素食團 / Halal / vegetarian capability | C14: 清真餐廳 6 家可用；素食可安排 | D14: halal_capable
A15: 報價幣種 / Quote currency | C15: TWD | D15: quote_currency
A16: 報價有效期 起 / Valid from | C16: 2027-01-01 | D16: quote_valid_from
A17: 報價有效期 止 / Valid until | C17: 2027-12-31 | D17: quote_valid_until
A18: 付款條件（訂金 / 尾款期限） / Payment terms | C18: 出發前 30 天付 30% 訂金，出發前 7 天付清 | D18: payment_terms
A19: 取消政策 / Cancellation policy | C19: 出發前 14 天取消收 30%…… | D19: cancellation_policy
A20: 旅行社責任險（保額） / Liability insurance (coverage) | D20: liability_insurance
A21: 報價是否含稅（VAT） / Price incl. VAT? | C21: Y | D21: price_includes_tax
A22: 其他說明 / Other notes | D22: notes

Sheet 2 飯店
A1: 2 飯店 Hotels
A2: 請按城市填寫可操作的團體飯店（每家每季一行）；建議覆蓋台北、宜蘭/礁溪、花蓮、台東、墾丁、高雄、台南、嘉義/阿里山、日月潭、台中、清境。價格為每間每晚淨價。
A3: 城市 City | B3: 飯店名稱（英文） Hotel name (EN) | C3: WEBUY 檔次參考 Tier seen in market | D3: 當地名稱 Local name | E3: 星級 Star | F3: 區域 / 商圈 Area | G3: 房型 Room type | H3: 季節檔 Season | I3: 適用日期 起 From | J3: 適用日期 止 To | K3: 雙人房 / 間 / 晚（TWD） Twin per room/night (TWD) | L3: 單人房 / 間 / 晚（TWD） Single per room/night (TWD) | M3: 三人房 / 間 / 晚（TWD） Triple per room/night (TWD) | N3: 加床（TWD） Extra bed (TWD) | O3: 含早餐 Breakfast incl. | P3: 早餐單價（TWD） Breakfast / pax (TWD) | Q3: 兒童政策（年齡 / 不佔床） Child policy | R3: 團體價最少間數 Min rooms for group rate | S3: 遊覽車可停 Coach parking | T3: 可保留房量（間 / 晚） Allotment (rooms/night) | U3: 釋放期（出發前天數） Release (days before) | V3: 備註（加價日 / 施工 / 新開） Notes
A4: city | B4: hotel_name_en | C4: webuy_tier | D4: hotel_name_local | E4: star | F4: area | G4: room_type | H4: season | I4: date_from | J4: date_to | K4: twin_per_room | L4: single_per_room | M4: triple_per_room | N4: extra_bed | O4: breakfast_incl | P4: breakfast_price | Q4: child_policy | R4: group_min_rooms | S4: coach_parking | T4: allotment | U4: release_days | V4: notes
A5: 台北 Taipei | B5: Caesar Park Hotel Taipei | D5: 台北凱撒大飯店 | E5: 4★ | F5: 台北車站 | G5: Superior Twin | H5: 平季 Shoulder | I5: 46447 | J5: 46568 | K5: 4200 | L5: 4000 | M5: 5200 | N5: 1000 | O5: Y | P5: 600 | Q5: 12 歲以下不佔床免費（不含早） | R5: 8 | S5: Y | T5: 15 | U5: 21 | V5: 跨年、國慶加價

Sheet 3 景點門票
A1: 3 景點門票 Attractions & Tickets
A2: 已預填 72 個台灣團體常用景點（灰色，WEBUY 整理的常見清單，非競品資料）。請填寫門票/團體價與限制；可在下方空行補充推薦景點。
A3: 城市 City | B3: 景點（英文） Attraction (EN) | C3: 景點（中文） Attraction (CN) | D3: 類別 Category | E3: 市場熱度 Market level | F3: 當地名稱 Local name | G3: 建議停留（小時） Suggested stay (h) | H3: 開放時間 Opening hours | I3: 休息日 Closed days | J3: 成人門票（TWD） Adult ticket (TWD) | K3: 兒童門票（TWD） Child ticket (TWD) | L3: 團體價 / 人（TWD） Group rate/pax (TWD) | M3: 團體價最少人數 Group min pax | N3: 免費政策（導遊 / 司機 / FOC） Free policy | O3: 需預約（提前天數，0=不需） Booking lead days | P3: 遊覽車可停 Coach parking | Q3: 最佳月份 / 季節限制 Best months / seasonal limits | R3: 適合 Suitable for | S3: 清真友好（祈禱室 / 餐） Muslim-friendly | T3: 備註（施工 / 關閉 / 替代景點） Notes
A4: city | B4: name_en | C4: name_cn | D4: category | E4: webuy_level | F4: name_local | G4: duration_h | H4: opening_hours | I4: closed_days | J4: adult_ticket | K4: child_ticket | L4: group_rate | M4: group_min_pax | N4: free_policy | O4: reservation_days | P4: coach_parking | Q4: best_months | R4: suitable | S4: halal_friendly | T4: notes
A5: 南投 Nantou | B5: Sun Moon Lake Ropeway | C5: 日月潭纜車 | D5: 纜車 | E5: 核心 Core | F5: 日月潭纜車 | G5: 1.5 | H5: 10:30–16:00 | I5: 每月第一個週三 | J5: 300 | K5: 250 | L5: 270 | M5: 20 | N5: 導遊司機免費 | O5: 3 | P5: Y | Q5: 全年 | R5: Both 均可 | S5: N | T5: 強風停駛，改遊湖船
A6: 台北 Taipei | B6: Taipei 101 Observatory | C6: 台北101觀景台 | D6: 觀景台
A7: 台北 Taipei | B7: National Palace Museum | C7: 國立故宮博物院 | D7: 博物館
A8: 台北 Taipei | B8: Chiang Kai-shek Memorial Hall | C8: 中正紀念堂 | D8: 史蹟
A9: 台北 Taipei | B9: Longshan Temple | C9: 艋舺龍山寺 | D9: 寺廟
A10: 台北 Taipei | B10: Ximending | C10: 西門町 | D10: 街區
A11: 台北 Taipei | B11: Shilin Night Market | C11: 士林夜市 | D11: 夜市
A12: 台北 Taipei | B12: Raohe Night Market | C12: 饒河街觀光夜市 | D12: 夜市
A13: 台北 Taipei | B13: Yangmingshan National Park | C13: 陽明山國家公園 | D13: 自然
A14: 台北 Taipei | B14: Beitou Hot Spring | C14: 北投溫泉 | D14: 溫泉
A15: 台北 Taipei | B15: Maokong Gondola | C15: 貓空纜車 | D15: 纜車
A16: 台北 Taipei | B16: Dadaocheng & Dihua Street | C16: 大稻埕·迪化街 | D16: 老街
A17: 台北 Taipei | B17: Huashan 1914 Creative Park | C17: 華山1914文創園區 | D17: 文創
... A77: 屏東 Pingtung | B77: National Museum of Marine Biology & Aquarium | C77: 國立海洋生物博物館 | D77: 博物館

Sheet 4 餐食
A1: 4 餐食 Meals
A2: 灰色為常見團餐（請對應報價、推薦餐廳）；黃色空行補充其他團餐與特色餐。價格為每人淨價，含稅。
A3: 城市 City | B3: 餐名 / 選單 Meal / menu | C3: 餐廳名稱 Restaurant | D3: 餐別 Meal | E3: 菜系 / 特色 Cuisine / highlight | F3: 成人 / 人（TWD） Adult/pax (TWD) | G3: 兒童 / 人（TWD） Child/pax (TWD) | H3: 最少人數 Min pax | I3: 可容納人數 Seating capacity | J3: 清真 Halal | K3: 素食可替換 Vegetarian option | L3: 可不含牛肉 No-beef option | M3: 遊覽車可停 Coach parking | N3: 備註 Notes
A4: city | B4: meal_name | C4: restaurant | D4: meal_type | E4: cuisine | F4: price_adult | G4: price_child | H4: min_pax | I4: capacity | J4: halal | K4: vegetarian | L4: no_beef | M4: coach_parking | N4: notes
A5: 台北 Taipei | B5: 台菜合菜（十菜一湯） | C5: 欣葉台菜 | D5: D | E5: 台菜 | F5: 650 | G5: 450 | H5: 10 | I5: 200 | J5: N | K5: Y | L5: Y | M5: Y | N5: 10 人一桌
A6: 台北 Taipei | B6: 鼎泰豐小籠包套餐
A7: 台北 Taipei | B7: 台菜合菜（10 人桌）
A8: 南投 Nantou | B8: 日月潭總統魚 / 奇力魚風味餐
A9: 嘉義 Chiayi | B9: 阿里山便當 / 山產合菜
A10: 台南 Tainan | B10: 台南小吃宴（擔仔麵、蝨目魚）
A11: 花蓮 Hualien | B11: 原住民風味餐
A12: 高雄 Kaohsiung | B12: 海鮮合菜
A13: 台中 Taichung | B13: 火鍋（涮涮鍋）
A14: 宜蘭 Yilan | B14: 溫泉會館自助晚餐

Sheet 5 用車交通
A1: 5 用車與交通 Transport
A2: 灰色為常用用車專案與環島常見路段。請按車型填價；高鐵/台鐵請填團體票價與訂位規則；山區路段請註明是否需換中巴。
A3: 專案 / 路段 Item / segment | B3: 方式 Mode | C3: 競品線路出現次數 Seen in market tours | D3: 車型 Vehicle | E3: 車程 / 航程 Duration | F3: 價格（TWD） Price (TWD) | G3: 計價單位 Price unit | H3: 已含（油/路橋/停車/司機食宿） Included | I3: 超時 / 小時（TWD） Overtime/h (TWD) | J3: 備註 Notes
A4: item | B4: mode | C4: market_seen | D4: vehicle | E4: duration | F4: price | G4: price_unit | H4: included | I4: ot_per_hour | J4: notes
A5: 遊覽車日租（10 小時） | B5: Coach | D5: 45 seats | E5: 10h | F5: 13000 | G5: 每車每天 | H5: 油資、過路費、停車費；司機食宿另計 | I5: 800 | J5: 阿里山、清境需換中巴
A6: 遊覽車日租（10 小時） | B6: Coach
A7: 桃園機場 TPE 接 / 送 | B7: Coach
A8: 環島 8 天包車 | B8: Coach
A9: 桃園機場 TPE → 台北市區 | B9: 遊覽車 Coach
A10: 台北 → 宜蘭（雪山隧道） | B10: 遊覽車 Coach
A11: 宜蘭 → 花蓮（蘇花改） | B11: 遊覽車 Coach
A12: 台北 → 花蓮 | B12: 台鐵 太魯閣/普悠瑪號 TRA
A13: 花蓮 → 台東（花東縱谷） | B13: 遊覽車 Coach
A14: 台東 → 墾丁（南迴） | B14: 遊覽車 Coach
A15: 墾丁 → 高雄 | B15: 遊覽車 Coach
A16: 高雄 → 台南 | B16: 遊覽車 Coach
A17: 台南 → 阿里山 | B17: 遊覽車 Coach（山區中巴）
... A26: 松山 TSA 機場接送 | B26: 遊覽車 Coach

Sheet 6 導遊領隊
A1: 6 導遊 / 領隊 / 小費 Guides & Tips
A2: 填寫導遊費用與建議小費（WEBUY 會寫進行程「不含」與「服務費」）。
A3: 角色 Role | B3: 語種 Language | C3: 日薪（TWD） Fee/day (TWD) | D3: 餐補 / 天（TWD） Meal allowance/day (TWD) | E3: 需另付住宿 Room needed | F3: 建議小費 / 人 / 天（TWD） Tips/pax/day (TWD) | G3: FOC 政策（如 15+1） FOC policy | H3: 備註 Notes
A4: role | B4: language | C4: fee_per_day | D4: meal_allowance | E4: room_needed | F4: tips_guideline | G4: foc_policy | H4: notes
A5: 中文導遊 Mandarin guide | B5: 中文 Mandarin | C5: 3000 | D5: 400 | E5: Y | F5: 300 | G5: 15+1（第 16 位免費） | H5: 小費導遊與司機合計
A6: 中文導遊 Mandarin guide
A7: 英文導遊 English guide
A8: 司機兼導遊 Driver-guide
A9: 送機 / 接機助理 Airport assistant

Sheet 7 購物與自費
A1: 7 購物站與自費 Shopping stops & Optional tours
A2: 請列出標準購物站、人頭費與「免購物」加價，以及常見自費專案價格，以便 WEBUY 做純玩與常規兩個版本。
A3: 名稱 Name | B3: 型別 Type | C3: 城市 City | D3: 停留（分鐘） Stay (min) | E3: 自費價格 / 人（TWD） Optional price/pax (TWD) | F3: 人頭費 / 人（TWD） Rebate per head (TWD) | G3: 佣金比例 Commission % | H3: 是否必進 Mandatory | I3: 備註（可否免購物 / 免購物加價） Notes (no-shopping surcharge)
A4: name | B4: type | C4: city | D4: stay_minutes | E4: price | F4: rebate_per_head | G4: commission_pct | H4: mandatory | I4: notes
A5: 茶葉（高山茶） | B5: 購物站 Shopping stop | C5: 南投 Nantou | D5: 60 | F5: 200 | G5: 0.1 | H5: Y | I5: 全程不進購物站每人加 TWD 1,500
A6: 茶葉（高山茶） | B6: 購物站 Shopping stop
A7: 鳳梨酥 / 伴手禮 | B7: 購物站 Shopping stop
A8: 珊瑚 / 寶石 | B8: 購物站 Shopping stop
A9: 台灣玉 / 玉石 | B9: 購物站 Shopping stop
A10: 靈芝 / 保健品 | B10: 購物站 Shopping stop
A11: 免稅店（昇恆昌） | B11: 購物站 Shopping stop
A12: 日月潭遊湖加纜車 | B12: 自費 Optional tour
A13: 阿里山日出小火車 | B13: 自費 Optional tour
A14: 台北 101 觀景台 | B14: 自費 Optional tour
A15: 溫泉湯屋 | B15: 自費 Optional tour

Sheet 8 季節節慶
A1: 8 季節與節慶 Seasons & Events
A2: 灰色為 WEBUY 掌握的季節視窗；請填 2027 確切日期、飯店加價與操作建議，可補充其他節慶。
A3: 季節 / 節慶 Season / event | B3: WEBUY 參考時間 Reference window | C3: 2027 確切日期 2027 exact dates | D3: 影響城市 Cities affected | E3: 飯店加價 % Hotel surcharge % | F3: 是否不能接團 Blackout | G3: 地接建議（必去 / 迴避 / 替代） DMC advice | H3: 備註 Notes
A4: event | B4: webuy_window | C4: dates_2027 | D4: city | E4: hotel_surcharge_pct | F4: blackout | G4: recommend | H4: notes
A5: 阿里山花季（櫻花） | B5: 3 月中 ~ 4 月中 | C5: 2027-03-15 ~ 04-15 | D5: 嘉義 阿里山 | E5: 0.2 | F5: N | G5: 假日管制，建議平日上山 | H5: 需換接駁車
A6: 春節 Lunar New Year | B6: 2027-02-05 ~ 02-10（以官方公佈為準）
A7: 元宵 / 平溪天燈節 | B7: 2027-02-20 前後
A8: 武陵櫻花季 | B8: 2 月中 ~ 3 月上旬
A9: 阿里山花季（櫻花） | B9: 3 月中 ~ 4 月中
A10: 清明連假 | B10: 2027-04-03 ~ 04-06
A11: 賞螢 / 油桐花 | B11: 4 月 ~ 5 月
A12: 梅雨季 | B12: 5 月 ~ 6 月
A13: 端午節 | B13: 2027-06-09 前後
A14: 颱風季 | B14: 7 月 ~ 9 月
A15: 暑假（國旅 / 陸客） | B15: 7 月 ~ 8 月
A16: 中秋節 | B16: 2027-09-15 前後
A17: 國慶日 | B17: 10 月 10 日
... A20: 太魯閣步道 / 蘇花公路管制 | B20: 不定期

Sheet 9 行程報價
A1: 9 行程報價 Package Quote（按 出發期 × 人數檔 一行）
A2: 對應 Lark Quotes / Quote_Lines。灰色為 WEBUY 詢價線路與人數檔；請按出發期段填寫每人淨價（同一線路不同季節可複製行）。行程細節請填「10 逐日行程」。綠色列自動計算。
A3: 詢價編號 RFQ code | B3: 線路骨架 Itinerary skeleton | C3: 天數 Days | D3: 飯店檔次 Hotel level | E3: 出發期 起 Departure from | F3: 出發期 止 Departure to | G3: 季節檔 Season | H3: 人數檔 Pax tier | I3: 幣種 Currency | J3: 成人 / 人（兩人一房） Adult/pax twin | K3: 單房差 Single supplement | L3: 兒童佔床 Child w/ bed | M3: 兒童不佔床 Child no bed | N3: 三人房 / 人 Triple/pax | O3: FOC（如 15+1） FOC | P3: SGD 參考價（自動） SGD ref. (auto) | Q3: 含餐（B/L/D 次數） Meals incl. (B/L/D) | R3: 含門票 Tickets incl. | S3: 含導遊 Guide incl. | T3: 含小費 Tips incl. | U3: 含國內段機票 / 高鐵 Domestic flight/rail incl. | V3: 購物站數 Shopping stops | W3: 備註（附加費 / 不含項） Notes
A4: rfq_code | B4: itinerary | C4: days | D4: hotel_level | E4: date_from | F4: date_to | G4: season | H4: pax_tier | I4: currency | J4: price_twin | K4: single_supp | L4: child_with_bed | M4: child_no_bed | N4: triple | O4: foc | P4: price_twin_sgd | Q4: meals_count | R4: incl_tickets | S4: incl_guide | T4: incl_tips | U4: incl_domestic_transport | V4: shopping_stops | W4: notes
A5: RFQ-TW8 | B5: 台北 2N > 花蓮 1N > 台東 1N > 高雄 1N > 日月潭 1N > 台北 1N | C5: 8 | D5: 4★ | E5: 46492 | F5: 46568 | G5: 平季 Shoulder | H5: 21–25 | I5: TWD | J5: 26000 | K5: 8000 | L5: 25000 | M5: 20000 | N5: 25500 | O5: 15+1 | P5: =IF(OR(J5="",I5=""),"",J5*INDEX(Lists!$B$21:$B$23,MATCH(I5,Lists!$A$21:$A$23,0))) -> 1066 | Q5: 6B 6L 5D | R5: Y | S5: Y | T5: N | U5: Y | V5: 3 | W5: 清明連假每人 +TWD 1,500
A6: RFQ-TW8 | B6: 台灣環島：台北 2N > 花蓮 1N > 台東 1N > 高雄 1N > 日月潭 1N > 台北 1N | C6: 8 | D6: 4★ | H6: 10–15 | P6: =IF(OR(J6="",I6=""),"",J6*INDEX(Lists!$B$21:$B$23,MATCH(I6,Lists!$A$21:$A$23,0)))
A7: RFQ-TW8 | B7: 台灣環島：台北 2N > 花蓮 1N > 台東 1N > 高雄 1N > 日月潭 1N > 台北 1N | C7: 8 | D7: 4★ | H7: 16–20 | P7: =IF(OR(J7="",I7=""),"",J7*INDEX(Lists!$B$21:$B$23,MATCH(I7,Lists!$A$21:$A$23,0)))
A8: RFQ-TW8 | B8: 台灣環島：台北 2N > 花蓮 1N > 台東 1N > 高雄 1N > 日月潭 1N > 台北 1N | C8: 8 | D8: 4★ | H8: 21–25 | P8: =IF(OR(J8="",I8=""),"",J8*INDEX(Lists!$B$21:$B$23,MATCH(I8,Lists!$A$21:$A$23,0)))
A9: RFQ-TW8 | B9: 台灣環島：台北 2N > 花蓮 1N > 台東 1N > 高雄 1N > 日月潭 1N > 台北 1N | C9: 8 | D9: 4★ | H9: 26–30 | P9: =IF(OR(J9="",I9=""),"",J9*INDEX(Lists!$B$21:$B$23,MATCH(I9,Lists!$A$21:$A$23,0)))
A10: RFQ-TW8 | B10: 台灣環島：台北 2N > 花蓮 1N > 台東 1N > 高雄 1N > 日月潭 1N > 台北 1N | C10: 8 | D10: 4★ | H10: 31–35 | P10: =IF(OR(J10="",I10=""),"",J10*INDEX(Lists!$B$21:$B$23,MATCH(I10,Lists!$A$21:$A$23,0)))
A11: RFQ-TW5 | B11: 北台灣：台北 3N（九份 / 野柳 / 十分）> 宜蘭礁溪 1N | C11: 5 | D11: 4★ | H11: 10–15 | P11: =IF(OR(J11="",I11=""),"",J11*INDEX(Lists!$B$21:$B$23,MATCH(I11,Lists!$A$21:$A$23,0)))
A12: RFQ-TW5 | B12: 北台灣：台北 3N（九份 / 野柳 / 十分）> 宜蘭礁溪 1N | C12: 5 | D12: 4★ | H12: 16–20 | P12: =IF(OR(J12="",I12=""),"",J12*INDEX(Lists!$B$21:$B$23,MATCH(I12,Lists!$A$21:$A$23,0)))
A13: RFQ-TW5 | B13: 北台灣：台北 3N（九份 / 野柳 / 十分）> 宜蘭礁溪 1N | C13: 5 | D13: 4★ | H13: 21–25 | P13: =IF(OR(J13="",I13=""),"",J13*INDEX(Lists!$B$21:$B$23,MATCH(I13,Lists!$A$21:$A$23,0)))
A14: RFQ-TW5 | B14: 北台灣：台北 3N（九份 / 野柳 / 十分）> 宜蘭礁溪 1N | C14: 5 | D14: 4★ | H14: 26–30 | P14: =IF(OR(J14="",I14=""),"",J14*INDEX(Lists!$B$21:$B$23,MATCH(I14,Lists!$A$21:$A$23,0)))
A15: RFQ-TW5 | B15: 北台灣：台北 3N（九份 / 野柳 / 十分）> 宜蘭礁溪 1N | C15: 5 | D15: 4★ | H15: 31–35 | P15: =IF(OR(J15="",I15=""),"",J15*INDEX(Lists!$B$21:$B$23,MATCH(I15,Lists!$A$21:$A$23,0)))
A16: RFQ-TW6 | B16: 中南部：台中 1N > 阿里山 1N > 台南 1N > 高雄 1N > 台北 1N | C16: 6 | D16: 4★ | H16: 10–15 | P16: =IF(OR(J16="",I16=""),"",J16*INDEX(Lists!$B$21:$B$23,MATCH(I16,Lists!$A$21:$A$23,0)))
A17: RFQ-TW6 | B17: 中南部：台中 1N > 阿里山 1N > 台南 1N > 高雄 1N > 台北 1N | C17: 6 | D17: 4★ | H17: 16–20 | P17: =IF(OR(J17="",I17=""),"",J17*INDEX(Lists!$B$21:$B$23,MATCH(I17,Lists!$A$21:$A$23,0)))
... A25: RFQ-TW6B | B25: 台北 + 日月潭 + 台中：台北 2N > 日月潭 1N > 台中 2N | C25: 6 | D25: 4★ | H25: 31–35 | P25: =IF(OR(J25="",I25=""),"",J25*INDEX(Lists!$B$21:$B$23,MATCH(I25,Lists!$A$21:$A$23,0)))
P26: =IF(OR(J26="",I26=""),"",J26*INDEX(Lists!$B$21:$B$23,MATCH(I26,Lists!$A$21:$A$23,0)))
P27: =IF(OR(J27="",I27=""),"",J27*INDEX(Lists!$B$21:$B$23,MATCH(I27,Lists!$A$21:$A$23,0)))
P28: =IF(OR(J28="",I28=""),"",J28*INDEX(Lists!$B$21:$B$23,MATCH(I28,Lists!$A$21:$A$23,0)))
P29: =IF(OR(J29="",I29=""),"",J29*INDEX(Lists!$B$21:$B$23,MATCH(I29,Lists!$A$21:$A$23,0)))
P30: =IF(OR(J30="",I30=""),"",J30*INDEX(Lists!$B$21:$B$23,MATCH(I30,Lists!$A$21:$A$23,0)))
P31: =IF(OR(J31="",I31=""),"",J31*INDEX(Lists!$B$21:$B$23,MATCH(I31,Lists!$A$21:$A$23,0)))
P32: =IF(OR(J32="",I32=""),"",J32*INDEX(Lists!$B$21:$B$23,MATCH(I32,Lists!$A$21:$A$23,0)))
P33: =IF(OR(J33="",I33=""),"",J33*INDEX(Lists!$B$21:$B$23,MATCH(I33,Lists!$A$21:$A$23,0)))
P34: =IF(OR(J34="",I34=""),"",J34*INDEX(Lists!$B$21:$B$23,MATCH(I34,Lists!$A$21:$A$23,0)))
P35: =IF(OR(J35="",I35=""),"",J35*INDEX(Lists!$B$21:$B$23,MATCH(I35,Lists!$A$21:$A$23,0)))
P36: =IF(OR(J36="",I36=""),"",J36*INDEX(Lists!$B$21:$B$23,MATCH(I36,Lists!$A$21:$A$23,0)))
P37: =IF(OR(J37="",I37=""),"",J37*INDEX(Lists!$B$21:$B$23,MATCH(I37,Lists!$A$21:$A$23,0)))
... P45: =IF(OR(J45="",I45=""),"",J45*INDEX(Lists!$B$21:$B$23,MATCH(I45,Lists!$A$21:$A$23,0)))

Sheet 10 逐日行程
A1: 10 逐日行程 Day-by-day Plan
A2: 每個詢價編號一組逐日行程，WEBUY 會用它生成雙語行程 PDF 並跑合理性校驗（景點歸屬、車程、季節）。
A3: 詢價編號 RFQ code | B3: 天 Day | C3: 城市路線 Route | D3: 交通（車程 / 航班） Transport | E3: 景點（用「3 景點門票」裡的名稱，頓號分隔） Attractions | F3: 早餐 Breakfast | G3: 午餐 Lunch | H3: 晚餐 Dinner | I3: 住宿飯店 Hotel | J3: 當天車程（小時） Driving hours | K3: 購物站 Shopping stop | L3: 備註（季節替代方案） Notes
A4: rfq_code | B4: day | C4: route | D4: transport | E4: attractions | F4: breakfast | G4: lunch | H4: dinner | I4: hotel | J4: driving_hours | K4: shopping | L4: notes
A5: RFQ-TW8 | B5: 3 | C5: 台北 > 宜蘭 > 花蓮 | D5: 遊覽車 3h | E5: 國立傳統藝術中心、清水斷崖、七星潭 | F5: 飯店 | G5: 宜蘭風味餐 | H5: 原住民風味餐 | I5: 花蓮翰品飯店 或同級 | J5: 3.5 | L5: 蘇花改管制時改搭火車

Sheet Lists
A1: 下拉選項（勿改）
A3: yn | B3: season | C3: currency | D3: star | E3: meal | F3: suit | G3: tier | H3: lang | I3: vehicle | J3: shoptype | K3: level
A4: Y | B4: 淡季 Low | C4: TWD | D4: 3★ | E4: B | F4: Group 團體 | G4: 10–15 | H4: 中文 Mandarin | I4: 9 seats (van) | J4: 購物站 Shopping stop | K4: 核心 Core
A5: N | B5: 平季 Shoulder | C5: USD | D5: 4★ | E5: L | F5: FIT 散客 | G5: 16–20 | H5: English | I5: 15 seats | J5: 自費 Optional tour | K5: 常見 Common
B6: 旺季 Peak | C6: SGD | D6: 5★ | E6: D | F6: Both 均可 | G6: 21–25 | H6: 粵語 Cantonese | I6: 25 seats | K6: 可選 Optional
B7: 節假 Holiday | D7: Resort | E7: Snack | G7: 26–30 | H7: Malay | I7: 35 seats | K7: 地接推薦 DMC pick
D8: 民宿 B&B | G8: 31–35 | H8: 日本語 | I8: 45 seats
D9: Glamping | G9: 36+
A20: 參考匯率（1 單位外幣 = ? SGD）
A21: TWD | B21: 0.041
A22: USD | B22: 1.29
A23: SGD | B23: 1
A24: 假設：2026-10 參考匯率，僅用於報價表「SGD 參考價」列；正式成本以 Lark FX_Rates 表為準（A4 自動重算）。
